{
    "insert": {
        "_<APIcall>_abort": "0",
        "_<APIcall>_abs": "1",
        "_<APIcall>_acos": "2",
        "_<APIcall>_append": "3",
        "_<APIcall>_assert": "4",
        "_<APIcall>_assign": "5",
        "_<APIcall>_at": "6",
        "_<APIcall>_atan": "7",
        "_<APIcall>_atan2": "8",
        "_<APIcall>_atoi": "9",
        "_<APIcall>_back": "10",
        "_<APIcall>_begin": "11",
        "_<APIcall>_c_str": "12",
        "_<APIcall>_ceil": "13",
        "_<APIcall>_cin": "14",
        "_<APIcall>_clear": "15",
        "_<APIcall>_clock": "16",
        "_<APIcall>_close": "17",
        "_<APIcall>_compare": "18",
        "_<APIcall>_copy": "19",
        "_<APIcall>_count": "20",
        "_<APIcall>_cout": "21",
        "_<APIcall>_data": "22",
        "_<APIcall>_div": "23",
        "_<APIcall>_empty": "24",
        "_<APIcall>_end": "25",
        "_<APIcall>_eof": "26",
        "_<APIcall>_erase": "27",
        "_<APIcall>_exit": "28",
        "_<APIcall>_exp": "29",
        "_<APIcall>_fabs": "30",
        "_<APIcall>_fail": "31",
        "_<APIcall>_fill": "32",
        "_<APIcall>_find": "33",
        "_<APIcall>_find_first_not_of": "34",
        "_<APIcall>_first": "35",
        "_<APIcall>_fixed": "36",
        "_<APIcall>_flags": "37",
        "_<APIcall>_flip": "38",
        "_<APIcall>_floor": "39",
        "_<APIcall>_flush": "40",
        "_<APIcall>_fmod": "41",
        "_<APIcall>_free": "42",
        "_<APIcall>_freopen": "43",
        "_<APIcall>_front": "44",
        "_<APIcall>_get": "45",
        "_<APIcall>_getchar": "46",
        "_<APIcall>_getline": "47",
        "_<APIcall>_gets": "48",
        "_<APIcall>_good": "49",
        "_<APIcall>_ignore": "50",
        "_<APIcall>_insert": "51",
        "_<APIcall>_isalnum": "52",
        "_<APIcall>_isalpha": "53",
        "_<APIcall>_isdigit": "54",
        "_<APIcall>_islower": "55",
        "_<APIcall>_isupper": "56",
        "_<APIcall>_length": "57",
        "_<APIcall>_log": "58",
        "_<APIcall>_lower_bound": "59",
        "_<APIcall>_main": "60",
        "_<APIcall>_malloc": "61",
        "_<APIcall>_memcmp": "62",
        "_<APIcall>_memcpy": "63",
        "_<APIcall>_memset": "64",
        "_<APIcall>_modf": "65",
        "_<APIcall>_npos": "66",
        "_<APIcall>_open": "67",
        "_<APIcall>_pop": "68",
        "_<APIcall>_pop_back": "69",
        "_<APIcall>_pop_front": "70",
        "_<APIcall>_pow": "71",
        "_<APIcall>_precision": "72",
        "_<APIcall>_push": "73",
        "_<APIcall>_push_back": "74",
        "_<APIcall>_push_front": "75",
        "_<APIcall>_put": "76",
        "_<APIcall>_putchar": "77",
        "_<APIcall>_puts": "78",
        "_<APIcall>_qsort": "79",
        "_<APIcall>_rand": "80",
        "_<APIcall>_rbegin": "81",
        "_<APIcall>_read": "82",
        "_<APIcall>_rem": "83",
        "_<APIcall>_remove": "84",
        "_<APIcall>_rend": "85",
        "_<APIcall>_replace": "86",
        "_<APIcall>_reserve": "87",
        "_<APIcall>_reset": "88",
        "_<APIcall>_resize": "89",
        "_<APIcall>_reverse": "90",
        "_<APIcall>_rfind": "91",
        "_<APIcall>_second": "92",
        "_<APIcall>_set": "93",
        "_<APIcall>_setf": "94",
        "_<APIcall>_setlocale": "95",
        "_<APIcall>_signal": "96",
        "_<APIcall>_size": "97",
        "_<APIcall>_sort": "98",
        "_<APIcall>_sqrt": "99",
        "_<APIcall>_srand": "100",
        "_<APIcall>_str": "101",
        "_<APIcall>_strchr": "102",
        "_<APIcall>_strcmp": "103",
        "_<APIcall>_strcpy": "104",
        "_<APIcall>_strlen": "105",
        "_<APIcall>_strncpy": "106",
        "_<APIcall>_strstr": "107",
        "_<APIcall>_substr": "108",
        "_<APIcall>_sum": "109",
        "_<APIcall>_swap": "110",
        "_<APIcall>_tan": "111",
        "_<APIcall>_time": "112",
        "_<APIcall>_tolower": "113",
        "_<APIcall>_top": "114",
        "_<APIcall>_toupper": "115",
        "_<APIcall>_unique": "116",
        "_<APIcall>_upper_bound": "117",
        "_<char>_": "118",
        "_<char_continue>_": "119",
        "_<id>_10@": "120",
        "_<id>_11@": "121",
        "_<id>_12@": "122",
        "_<id>_13@": "123",
        "_<id>_14@": "124",
        "_<id>_15@": "125",
        "_<id>_16@": "126",
        "_<id>_17@": "127",
        "_<id>_18@": "128",
        "_<id>_19@": "129",
        "_<id>_1@": "130",
        "_<id>_20@": "131",
        "_<id>_21@": "132",
        "_<id>_22@": "133",
        "_<id>_23@": "134",
        "_<id>_24@": "135",
        "_<id>_25@": "136",
        "_<id>_26@": "137",
        "_<id>_27@": "138",
        "_<id>_28@": "139",
        "_<id>_29@": "140",
        "_<id>_2@": "141",
        "_<id>_30@": "142",
        "_<id>_31@": "143",
        "_<id>_32@": "144",
        "_<id>_33@": "145",
        "_<id>_34@": "146",
        "_<id>_35@": "147",
        "_<id>_3@": "148",
        "_<id>_4@": "149",
        "_<id>_5@": "150",
        "_<id>_6@": "151",
        "_<id>_7@": "152",
        "_<id>_8@": "153",
        "_<id>_9@": "154",
        "_<keyword>_EOF": "155",
        "_<keyword>_NULL": "156",
        "_<keyword>_and": "157",
        "_<keyword>_asm": "158",
        "_<keyword>_break": "159",
        "_<keyword>_case": "160",
        "_<keyword>_catch": "161",
        "_<keyword>_const": "162",
        "_<keyword>_continue": "163",
        "_<keyword>_do": "164",
        "_<keyword>_else": "165",
        "_<keyword>_endl": "166",
        "_<keyword>_false": "167",
        "_<keyword>_for": "168",
        "_<keyword>_goto": "169",
        "_<keyword>_if": "170",
        "_<keyword>_inline": "171",
        "_<keyword>_new": "172",
        "_<keyword>_not": "173",
        "_<keyword>_or": "174",
        "_<keyword>_register": "175",
        "_<keyword>_requires": "176",
        "_<keyword>_return": "177",
        "_<keyword>_sizeof": "178",
        "_<keyword>_static": "179",
        "_<keyword>_static_cast": "180",
        "_<keyword>_template": "181",
        "_<keyword>_this": "182",
        "_<keyword>_throw": "183",
        "_<keyword>_true": "184",
        "_<keyword>_try": "185",
        "_<keyword>_void": "186",
        "_<keyword>_while": "187",
        "_<keyword>_xor": "188",
        "_<number>_#": "189",
        "_<op>_!": "190",
        "_<op>_!=": "191",
        "_<op>_#": "192",
        "_<op>_%": "193",
        "_<op>_%=": "194",
        "_<op>_&": "195",
        "_<op>_&&": "196",
        "_<op>_&=": "197",
        "_<op>_(": "198",
        "_<op>_)": "199",
        "_<op>_*": "200",
        "_<op>_**": "201",
        "_<op>_*=": "202",
        "_<op>_+": "203",
        "_<op>_++": "204",
        "_<op>_+=": "205",
        "_<op>_,": "206",
        "_<op>_-": "207",
        "_<op>_--": "208",
        "_<op>_-=": "209",
        "_<op>_->": "210",
        "_<op>_.": "211",
        "_<op>_/": "212",
        "_<op>_/=": "213",
        "_<op>_:": "214",
        "_<op>_;": "215",
        "_<op>_<": "216",
        "_<op>_<<": "217",
        "_<op>_<=": "218",
        "_<op>_=": "219",
        "_<op>_==": "220",
        "_<op>_>": "221",
        "_<op>_>=": "222",
        "_<op>_>>": "223",
        "_<op>_?": "224",
        "_<op>_TiLddE": "225",
        "_<op>_[": "226",
        "_<op>_]": "227",
        "_<op>_^": "228",
        "_<op>_{": "229",
        "_<op>_|": "230",
        "_<op>_|=": "231",
        "_<op>_||": "232",
        "_<op>_}": "233",
        "_<string>_": "234",
        "_<type>_bool": "235",
        "_<type>_char": "236",
        "_<type>_double": "237",
        "_<type>_float": "238",
        "_<type>_int": "239",
        "_<type>_long": "240",
        "_<type>_short": "241",
        "_<type>_signed": "242",
        "_<type>_string": "243",
        "_<type>_unsigned": "244"
    },
    "replace": {
        "_<APIcall>_abort": "245",
        "_<APIcall>_abs": "246",
        "_<APIcall>_acos": "247",
        "_<APIcall>_append": "248",
        "_<APIcall>_assert": "249",
        "_<APIcall>_assign": "250",
        "_<APIcall>_at": "251",
        "_<APIcall>_atan": "252",
        "_<APIcall>_atan2": "253",
        "_<APIcall>_atoi": "254",
        "_<APIcall>_back": "255",
        "_<APIcall>_begin": "256",
        "_<APIcall>_c_str": "257",
        "_<APIcall>_ceil": "258",
        "_<APIcall>_cin": "259",
        "_<APIcall>_clear": "260",
        "_<APIcall>_clock": "261",
        "_<APIcall>_close": "262",
        "_<APIcall>_compare": "263",
        "_<APIcall>_copy": "264",
        "_<APIcall>_count": "265",
        "_<APIcall>_cout": "266",
        "_<APIcall>_data": "267",
        "_<APIcall>_div": "268",
        "_<APIcall>_empty": "269",
        "_<APIcall>_end": "270",
        "_<APIcall>_eof": "271",
        "_<APIcall>_erase": "272",
        "_<APIcall>_exit": "273",
        "_<APIcall>_exp": "274",
        "_<APIcall>_fabs": "275",
        "_<APIcall>_fail": "276",
        "_<APIcall>_fill": "277",
        "_<APIcall>_find": "278",
        "_<APIcall>_find_first_not_of": "279",
        "_<APIcall>_first": "280",
        "_<APIcall>_fixed": "281",
        "_<APIcall>_flags": "282",
        "_<APIcall>_flip": "283",
        "_<APIcall>_floor": "284",
        "_<APIcall>_flush": "285",
        "_<APIcall>_fmod": "286",
        "_<APIcall>_free": "287",
        "_<APIcall>_freopen": "288",
        "_<APIcall>_front": "289",
        "_<APIcall>_get": "290",
        "_<APIcall>_getchar": "291",
        "_<APIcall>_getline": "292",
        "_<APIcall>_gets": "293",
        "_<APIcall>_good": "294",
        "_<APIcall>_ignore": "295",
        "_<APIcall>_insert": "296",
        "_<APIcall>_isalnum": "297",
        "_<APIcall>_isalpha": "298",
        "_<APIcall>_isdigit": "299",
        "_<APIcall>_islower": "300",
        "_<APIcall>_isupper": "301",
        "_<APIcall>_length": "302",
        "_<APIcall>_log": "303",
        "_<APIcall>_lower_bound": "304",
        "_<APIcall>_main": "305",
        "_<APIcall>_malloc": "306",
        "_<APIcall>_memcmp": "307",
        "_<APIcall>_memcpy": "308",
        "_<APIcall>_memset": "309",
        "_<APIcall>_modf": "310",
        "_<APIcall>_npos": "311",
        "_<APIcall>_open": "312",
        "_<APIcall>_pop": "313",
        "_<APIcall>_pop_back": "314",
        "_<APIcall>_pop_front": "315",
        "_<APIcall>_pow": "316",
        "_<APIcall>_precision": "317",
        "_<APIcall>_push": "318",
        "_<APIcall>_push_back": "319",
        "_<APIcall>_push_front": "320",
        "_<APIcall>_put": "321",
        "_<APIcall>_putchar": "322",
        "_<APIcall>_puts": "323",
        "_<APIcall>_qsort": "324",
        "_<APIcall>_rand": "325",
        "_<APIcall>_rbegin": "326",
        "_<APIcall>_read": "327",
        "_<APIcall>_rem": "328",
        "_<APIcall>_remove": "329",
        "_<APIcall>_rend": "330",
        "_<APIcall>_replace": "331",
        "_<APIcall>_reserve": "332",
        "_<APIcall>_reset": "333",
        "_<APIcall>_resize": "334",
        "_<APIcall>_reverse": "335",
        "_<APIcall>_rfind": "336",
        "_<APIcall>_second": "337",
        "_<APIcall>_set": "338",
        "_<APIcall>_setf": "339",
        "_<APIcall>_setlocale": "340",
        "_<APIcall>_signal": "341",
        "_<APIcall>_size": "342",
        "_<APIcall>_sort": "343",
        "_<APIcall>_sqrt": "344",
        "_<APIcall>_srand": "345",
        "_<APIcall>_str": "346",
        "_<APIcall>_strchr": "347",
        "_<APIcall>_strcmp": "348",
        "_<APIcall>_strcpy": "349",
        "_<APIcall>_strlen": "350",
        "_<APIcall>_strncpy": "351",
        "_<APIcall>_strstr": "352",
        "_<APIcall>_substr": "353",
        "_<APIcall>_sum": "354",
        "_<APIcall>_swap": "355",
        "_<APIcall>_tan": "356",
        "_<APIcall>_time": "357",
        "_<APIcall>_tolower": "358",
        "_<APIcall>_top": "359",
        "_<APIcall>_toupper": "360",
        "_<APIcall>_unique": "361",
        "_<APIcall>_upper_bound": "362",
        "_<char>_": "363",
        "_<char_continue>_": "364",
        "_<id>_10@": "365",
        "_<id>_11@": "366",
        "_<id>_12@": "367",
        "_<id>_13@": "368",
        "_<id>_14@": "369",
        "_<id>_15@": "370",
        "_<id>_16@": "371",
        "_<id>_17@": "372",
        "_<id>_18@": "373",
        "_<id>_19@": "374",
        "_<id>_1@": "375",
        "_<id>_20@": "376",
        "_<id>_21@": "377",
        "_<id>_22@": "378",
        "_<id>_23@": "379",
        "_<id>_24@": "380",
        "_<id>_25@": "381",
        "_<id>_26@": "382",
        "_<id>_27@": "383",
        "_<id>_28@": "384",
        "_<id>_29@": "385",
        "_<id>_2@": "386",
        "_<id>_30@": "387",
        "_<id>_31@": "388",
        "_<id>_32@": "389",
        "_<id>_33@": "390",
        "_<id>_34@": "391",
        "_<id>_35@": "392",
        "_<id>_3@": "393",
        "_<id>_4@": "394",
        "_<id>_5@": "395",
        "_<id>_6@": "396",
        "_<id>_7@": "397",
        "_<id>_8@": "398",
        "_<id>_9@": "399",
        "_<keyword>_EOF": "400",
        "_<keyword>_NULL": "401",
        "_<keyword>_and": "402",
        "_<keyword>_asm": "403",
        "_<keyword>_break": "404",
        "_<keyword>_case": "405",
        "_<keyword>_catch": "406",
        "_<keyword>_const": "407",
        "_<keyword>_continue": "408",
        "_<keyword>_do": "409",
        "_<keyword>_else": "410",
        "_<keyword>_endl": "411",
        "_<keyword>_false": "412",
        "_<keyword>_for": "413",
        "_<keyword>_goto": "414",
        "_<keyword>_if": "415",
        "_<keyword>_inline": "416",
        "_<keyword>_new": "417",
        "_<keyword>_not": "418",
        "_<keyword>_or": "419",
        "_<keyword>_register": "420",
        "_<keyword>_requires": "421",
        "_<keyword>_return": "422",
        "_<keyword>_sizeof": "423",
        "_<keyword>_static": "424",
        "_<keyword>_static_cast": "425",
        "_<keyword>_template": "426",
        "_<keyword>_this": "427",
        "_<keyword>_throw": "428",
        "_<keyword>_true": "429",
        "_<keyword>_try": "430",
        "_<keyword>_void": "431",
        "_<keyword>_while": "432",
        "_<keyword>_xor": "433",
        "_<number>_#": "434",
        "_<op>_!": "435",
        "_<op>_!=": "436",
        "_<op>_#": "437",
        "_<op>_%": "438",
        "_<op>_%=": "439",
        "_<op>_&": "440",
        "_<op>_&&": "441",
        "_<op>_&=": "442",
        "_<op>_(": "443",
        "_<op>_)": "444",
        "_<op>_*": "445",
        "_<op>_**": "446",
        "_<op>_*=": "447",
        "_<op>_+": "448",
        "_<op>_++": "449",
        "_<op>_+=": "450",
        "_<op>_,": "451",
        "_<op>_-": "452",
        "_<op>_--": "453",
        "_<op>_-=": "454",
        "_<op>_->": "455",
        "_<op>_.": "456",
        "_<op>_/": "457",
        "_<op>_/=": "458",
        "_<op>_:": "459",
        "_<op>_;": "460",
        "_<op>_<": "461",
        "_<op>_<<": "462",
        "_<op>_<=": "463",
        "_<op>_=": "464",
        "_<op>_==": "465",
        "_<op>_>": "466",
        "_<op>_>=": "467",
        "_<op>_>>": "468",
        "_<op>_?": "469",
        "_<op>_TiLddE": "470",
        "_<op>_[": "471",
        "_<op>_]": "472",
        "_<op>_^": "473",
        "_<op>_{": "474",
        "_<op>_|": "475",
        "_<op>_|=": "476",
        "_<op>_||": "477",
        "_<op>_}": "478",
        "_<string>_": "479",
        "_<type>_bool": "480",
        "_<type>_char": "481",
        "_<type>_double": "482",
        "_<type>_float": "483",
        "_<type>_int": "484",
        "_<type>_long": "485",
        "_<type>_short": "486",
        "_<type>_signed": "487",
        "_<type>_string": "488",
        "_<type>_unsigned": "489"
    }
}